make_figures_great_again/__init__.py
make_figures_great_again/the_best_colors/__init__.py
make_figures_great_again/the_best_colors/the_best_colors.py
make_figures_great_again/the_best_functions/__init__.py
make_figures_great_again/the_best_functions/the_best_functions.py
make_figures_great_again-0.2dev.dist-info/DESCRIPTION.rst
make_figures_great_again-0.2dev.dist-info/METADATA
make_figures_great_again-0.2dev.dist-info/RECORD
make_figures_great_again-0.2dev.dist-info/WHEEL
make_figures_great_again-0.2dev.dist-info/metadata.json
make_figures_great_again-0.2dev.dist-info/top_level.txt
