Metadata-Version: 2.0
Name: make-figures-great-again
Version: 0.2dev
Summary: Color palettes for Python
Home-page: https://www.donaldjtrump.com/
Author: author
Author-email: author@email.com
License: UNKNOWN
Platform: UNKNOWN
Classifier: License :: OSI Approved :: MIT License
Classifier: Programming Language :: Python
Classifier: Programming Language :: Python :: 2
Classifier: Programming Language :: Python :: 2.6
Classifier: Programming Language :: Python :: 2.7
Classifier: Programming Language :: Python :: 3
Classifier: Programming Language :: Python :: 3.3
Classifier: Programming Language :: Python :: 3.4
Classifier: Topic :: Scientific/Engineering :: Visualization
Requires-Dist: matplotlib
Requires-Dist: palettable
